{
 "title": {
    "english": "Glossary",
    "turkish": "-",
    "arabic": "-"
  },
 "segment": "primary",
 "userType": ["student"],
 "pageCount": 1,
 "pages": {
    "page01": {
      "pageType": "screenshot",
      "imgId": "PSG001.png",
      "pageTitle": {
        "english": "",
        "turkish": "",
        "arabic": ""
      },
      "paragraphs":{
        "paragraph01": {
          "number": 1,
          "numberPosTop": 2,
          "numberPosLeft": 1,
          "text":{
            "english": "The Glossary contains all core vocabulary in a level. Click on a letter to go to the words beginning with that letter in the Glossary.",
            "turkish": "-",
            "arabic": "-"
          }
        },
        "paragraph02": {
          "number": 2,
          "numberPosTop": 13,
          "numberPosLeft": 12,
          "text":{
            "english": "Type a word in the text box to search for a word. The Glossary automatically searches for the word.",
            "turkish": "-",
            "arabic": "-"
          }
        },
        "paragraph03": {
          "number": 3,
          "numberPosTop": 36,
          "numberPosLeft": 1,
          "text":{
            "english": "Scroll through the menu and choose a word to see the picture.",
            "turkish": "-",
            "arabic": "-"
          }
        },
        "paragraph04": {
          "number": 4,
          "numberPosTop": 42,
          "numberPosLeft": 23,
          "text":{
            "english": "Click the icon to hear the audio, if available.",
            "turkish": "-",
            "arabic": "-"
          }
        }
      }
    }
  }
}